[
    {
        "id": "m43517698312",
        "sellerId": "238418097",
        "buyerId": "",
        "status": "ITEM_STATUS_ON_SALE",
        "name": "大貫妙子　都会／くすりをたくさん",
        "price": "5900",
        "created": "1661342125",
        "updated": "1661561457",
        "thumbnails": [
            "https://static.mercdn.net/c!/w=240,f=webp/thumb/photos/m43517698312_1.jpg?1661342125"
        ],
        "itemType": "ITEM_TYPE_MERCARI",
        "itemConditionId": "3",
        "shippingPayerId": "2"
    },
    {
        "id": "m61738503104",
        "sellerId": "969498383",
        "buyerId": "",
        "status": "ITEM_STATUS_ON_SALE",
        "name": "大貫妙子 - MIGNONNE (クリア・ヴァイナル仕様)",
        "price": "12800",
        "created": "1661099600",
        "updated": "1661555564",
        "thumbnails": [
            "https://static.mercdn.net/c!/w=240,f=webp/thumb/photos/m61738503104_1.jpg?1661099600"
        ],
        "itemType": "ITEM_TYPE_MERCARI",
        "itemConditionId": "1",
        "shippingPayerId": "2"
    },
    {
        "id": "m59528873630",
        "sellerId": "388161373",
        "buyerId": "",
        "status": "ITEM_STATUS_ON_SALE",
        "name": "彼と彼女のソネット　原田知世　大貫妙子",
        "price": "2200",
        "created": "1660701105",
        "updated": "1661521454",
        "thumbnails": [
            "https://static.mercdn.net/c!/w=240,f=webp/thumb/photos/m59528873630_1.jpg?1660701105"
        ],
        "itemType": "ITEM_TYPE_MERCARI",
        "itemConditionId": "2",
        "shippingPayerId": "2"
    },
    {
        "id": "m87843491734",
        "sellerId": "152900487",
        "buyerId": "",
        "status": "ITEM_STATUS_ON_SALE",
        "name": "丸山圭子 7 菊池桃子 西村知美 吉永敬子 子猫物語 詞 大貫妙子 曲 坂本龍一",
        "price": "1500",
        "created": "1661229737",
        "updated": "1661515332",
        "thumbnails": [
            "https://static.mercdn.net/c!/w=240,f=webp/thumb/photos/m87843491734_1.jpg?1661229737"
        ],
        "itemType": "ITEM_TYPE_MERCARI",
        "itemConditionId": "4",
        "shippingPayerId": "2"
    },
    {
        "id": "m12477662446",
        "sellerId": "356934164",
        "buyerId": "",
        "status": "ITEM_STATUS_ON_SALE",
        "name": "【超美品】大貫妙子　SUNSHOWER  レコード　GW-4107  PANAM",
        "price": "17000",
        "created": "1659746530",
        "updated": "1661510116",
        "thumbnails": [
            "https://static.mercdn.net/c!/w=240,f=webp/thumb/photos/m12477662446_1.jpg?1659746530"
        ],
        "itemType": "ITEM_TYPE_MERCARI",
        "itemConditionId": "2",
        "shippingPayerId": "2"
    },
    {
        "id": "m51777018124",
        "sellerId": "344865471",
        "buyerId": "",
        "status": "ITEM_STATUS_ON_SALE",
        "name": "[新品 カセット] SUNSHOWER / TAEKO ONUKI / 大貫妙子",
        "price": "6999",
        "created": "1661502026",
        "updated": "1661502026",
        "thumbnails": [
            "https://static.mercdn.net/c!/w=240,f=webp/thumb/photos/m51777018124_1.jpg?1661502026"
        ],
        "itemType": "ITEM_TYPE_MERCARI",
        "itemConditionId": "1",
        "shippingPayerId": "2"
    },
    {
        "id": "m80031797765",
        "sellerId": "618058458",
        "buyerId": "",
        "status": "ITEM_STATUS_ON_SALE",
        "name": "レコード　オリジナル見本盤　大貫妙子　ミニヨン　mignonne LP",
        "price": "28200",
        "created": "1656207827",
        "updated": "1661492100",
        "thumbnails": [
            "https://static.mercdn.net/c!/w=240,f=webp/thumb/photos/m80031797765_1.jpg?1656207827"
        ],
        "itemType": "ITEM_TYPE_MERCARI",
        "itemConditionId": "4",
        "shippingPayerId": "2"
    },
    {
        "id": "m54418302220",
        "sellerId": "344865471",
        "buyerId": "",
        "status": "ITEM_STATUS_ON_SALE",
        "name": "[新品 7\"] 都会 / 何もいらないBlue Vinyl / 大貫妙子",
        "price": "4700",
        "created": "1661478429",
        "updated": "1661478429",
        "thumbnails": [
            "https://static.mercdn.net/c!/w=240,f=webp/thumb/photos/m54418302220_1.jpg?1661478429"
        ],
        "itemType": "ITEM_TYPE_MERCARI",
        "itemConditionId": "1",
        "shippingPayerId": "2"
    },
    {
        "id": "m69907985409",
        "sellerId": "136129521",
        "buyerId": "",
        "status": "ITEM_STATUS_ON_SALE",
        "name": "flexlife 3枚セットSPARKLE 都会　大貫妙子　山下達郎　レコード",
        "price": "6299",
        "created": "1661255645",
        "updated": "1661570470",
        "thumbnails": [
            "https://static.mercdn.net/c!/w=240,f=webp/thumb/photos/m69907985409_1.jpg?1661255645"
        ],
        "itemType": "ITEM_TYPE_MERCARI",
        "itemConditionId": "2",
        "shippingPayerId": "2"
    },
    {
        "id": "m19890750317",
        "sellerId": "119745109",
        "buyerId": "",
        "status": "ITEM_STATUS_ON_SALE",
        "name": "【カセットテープ】大貫妙子「クラシックス」",
        "price": "4590",
        "created": "1660482007",
        "updated": "1661434851",
        "thumbnails": [
            "https://static.mercdn.net/c!/w=240,f=webp/thumb/photos/m19890750317_1.jpg?1660482007"
        ],
        "itemType": "ITEM_TYPE_MERCARI",
        "itemConditionId": "4",
        "shippingPayerId": "2"
    },
    {
        "id": "m57700421173",
        "sellerId": "864149073",
        "buyerId": "",
        "status": "ITEM_STATUS_ON_SALE",
        "name": "大貫妙子/竹内まりや　EPレコード3枚セット",
        "price": "6500",
        "created": "1661408450",
        "updated": "1661408450",
        "thumbnails": [
            "https://static.mercdn.net/c!/w=240,f=webp/thumb/photos/m57700421173_1.jpg?1661408450"
        ],
        "itemType": "ITEM_TYPE_MERCARI",
        "itemConditionId": "4",
        "shippingPayerId": "2"
    },
    {
        "id": "m62641304061",
        "sellerId": "273842493",
        "buyerId": "",
        "status": "ITEM_STATUS_ON_SALE",
        "name": "帯付き【シニフィエ SIGNIFIE/大貫妙子】LPレコード",
        "price": "2500",
        "created": "1654764947",
        "updated": "1661394449",
        "thumbnails": [
            "https://static.mercdn.net/c!/w=240,f=webp/thumb/photos/m62641304061_1.jpg?1654764947"
        ],
        "itemType": "ITEM_TYPE_MERCARI",
        "itemConditionId": "4",
        "shippingPayerId": "2"
    },
    {
        "id": "m64065724883",
        "sellerId": "290205888",
        "buyerId": "",
        "status": "ITEM_STATUS_ON_SALE",
        "name": "【美品LP】大貫妙子★ロマンティック★レコード",
        "price": "4000",
        "created": "1661334908",
        "updated": "1661337698",
        "thumbnails": [
            "https://static.mercdn.net/c!/w=240,f=webp/thumb/photos/m64065724883_1.jpg?1661334908"
        ],
        "itemType": "ITEM_TYPE_MERCARI",
        "itemConditionId": "4",
        "shippingPayerId": "2"
    },
    {
        "id": "m20370443104",
        "sellerId": "290205888",
        "buyerId": "",
        "status": "ITEM_STATUS_ON_SALE",
        "name": "【美品LP】大貫妙子★アヴァンチュール★レコード",
        "price": "2500",
        "created": "1661334595",
        "updated": "1661337717",
        "thumbnails": [
            "https://static.mercdn.net/c!/w=240,f=webp/thumb/photos/m20370443104_1.jpg?1661334595"
        ],
        "itemType": "ITEM_TYPE_MERCARI",
        "itemConditionId": "3",
        "shippingPayerId": "2"
    },
    {
        "id": "m36166450523",
        "sellerId": "864149073",
        "buyerId": "",
        "status": "ITEM_STATUS_ON_SALE",
        "name": "大貫妙子　COMIN SOON レコード",
        "price": "3000",
        "created": "1660380301",
        "updated": "1661330684",
        "thumbnails": [
            "https://static.mercdn.net/c!/w=240,f=webp/thumb/photos/m36166450523_1.jpg?1660380301"
        ],
        "itemType": "ITEM_TYPE_MERCARI",
        "itemConditionId": "3",
        "shippingPayerId": "2"
    },
    {
        "id": "m29516904924",
        "sellerId": "143448580",
        "buyerId": "",
        "status": "ITEM_STATUS_ON_SALE",
        "name": "LP 大貫妙子 Taeko Ohnuki アヴァンチュール Aventure",
        "price": "2800",
        "created": "1661329750",
        "updated": "1661329750",
        "thumbnails": [
            "https://static.mercdn.net/c!/w=240,f=webp/thumb/photos/m29516904924_1.jpg?1661329750"
        ],
        "itemType": "ITEM_TYPE_MERCARI",
        "itemConditionId": "4",
        "shippingPayerId": "2"
    },
    {
        "id": "m83422247503",
        "sellerId": "505476324",
        "buyerId": "",
        "status": "ITEM_STATUS_ON_SALE",
        "name": "大貫妙子「グレイ・スカイズ」アナログレコード",
        "price": "5000",
        "created": "1655359341",
        "updated": "1661306093",
        "thumbnails": [
            "https://static.mercdn.net/c!/w=240,f=webp/thumb/photos/m83422247503_1.jpg?1655359341"
        ],
        "itemType": "ITEM_TYPE_MERCARI",
        "itemConditionId": "3",
        "shippingPayerId": "2"
    },
    {
        "id": "m80799309606",
        "sellerId": "530067491",
        "buyerId": "",
        "status": "ITEM_STATUS_ON_SALE",
        "name": "送料込　大貫妙子　都会 / 何もいらない　7インチレコード 未開封新品",
        "price": "4790",
        "created": "1661301549",
        "updated": "1661301549",
        "thumbnails": [
            "https://static.mercdn.net/c!/w=240,f=webp/thumb/photos/m80799309606_1.jpg?1661301549"
        ],
        "itemType": "ITEM_TYPE_MERCARI",
        "itemConditionId": "1",
        "shippingPayerId": "2"
    },
    {
        "id": "m89123147487",
        "sellerId": "572987782",
        "buyerId": "",
        "status": "ITEM_STATUS_ON_SALE",
        "name": "大貫妙子／カイエ　　LPレコード",
        "price": "2680",
        "created": "1661256310",
        "updated": "1661295114",
        "thumbnails": [
            "https://static.mercdn.net/c!/w=240,f=webp/thumb/photos/m89123147487_1.jpg?1661295114"
        ],
        "itemType": "ITEM_TYPE_MERCARI",
        "itemConditionId": "4",
        "shippingPayerId": "2"
    },
    {
        "id": "m68679465750",
        "sellerId": "943674316",
        "buyerId": "",
        "status": "ITEM_STATUS_ON_SALE",
        "name": "大貫妙子　クリシェ　LP",
        "price": "2700",
        "created": "1658707300",
        "updated": "1661247931",
        "thumbnails": [
            "https://static.mercdn.net/c!/w=240,f=webp/thumb/photos/m68679465750_1.jpg?1658707300"
        ],
        "itemType": "ITEM_TYPE_MERCARI",
        "itemConditionId": "3",
        "shippingPayerId": "2"
    },
    {
        "id": "m21672184874",
        "sellerId": "844798166",
        "buyerId": "",
        "status": "ITEM_STATUS_ON_SALE",
        "name": "大貫妙子 グレイスカイズ GREY SKIES レコード 帯付き",
        "price": "14000",
        "created": "1650364792",
        "updated": "1661164683",
        "thumbnails": [
            "https://static.mercdn.net/c!/w=240,f=webp/thumb/photos/m21672184874_1.jpg?1650364792"
        ],
        "itemType": "ITEM_TYPE_MERCARI",
        "itemConditionId": "3",
        "shippingPayerId": "2"
    },
    {
        "id": "m17955228720",
        "sellerId": "276568353",
        "buyerId": "",
        "status": "ITEM_STATUS_ON_SALE",
        "name": "コパン／大貫妙子〈ミャージックテープ〉【希少テープ】",
        "price": "4000",
        "created": "1660553401",
        "updated": "1661153155",
        "thumbnails": [
            "https://static.mercdn.net/c!/w=240,f=webp/thumb/photos/m17955228720_1.jpg?1660553401"
        ],
        "itemType": "ITEM_TYPE_MERCARI",
        "itemConditionId": "3",
        "shippingPayerId": "2"
    },
    {
        "id": "m38198108224",
        "sellerId": "845329749",
        "buyerId": "",
        "status": "ITEM_STATUS_ON_SALE",
        "name": "LPレコード名盤‼️【大貫妙子 シニフィエ】1983年初回国内オリジナル盤帯付き",
        "price": "2900",
        "created": "1642506553",
        "updated": "1661131556",
        "thumbnails": [
            "https://static.mercdn.net/c!/w=240,f=webp/thumb/photos/m38198108224_1.jpg?1642506553"
        ],
        "itemType": "ITEM_TYPE_MERCARI",
        "itemConditionId": "3",
        "shippingPayerId": "2"
    },
    {
        "id": "m33606492084",
        "sellerId": "268408873",
        "buyerId": "",
        "status": "ITEM_STATUS_ON_SALE",
        "name": "EARLY  TIMES 1976−77／大貫妙子　初盤LPレコード",
        "price": "3000",
        "created": "1660006811",
        "updated": "1661120346",
        "thumbnails": [
            "https://static.mercdn.net/c!/w=240,f=webp/thumb/photos/m33606492084_1.jpg?1660006811"
        ],
        "itemType": "ITEM_TYPE_MERCARI",
        "itemConditionId": "4",
        "shippingPayerId": "2"
    },
    {
        "id": "m12769546671",
        "sellerId": "952228755",
        "buyerId": "",
        "status": "ITEM_STATUS_ON_SALE",
        "name": "大貫妙子　レコード　SUNSHWER 新品　未使用❗️",
        "price": "11000",
        "created": "1661084475",
        "updated": "1661084475",
        "thumbnails": [
            "https://static.mercdn.net/c!/w=240,f=webp/thumb/photos/m12769546671_1.jpg?1661084475"
        ],
        "itemType": "ITEM_TYPE_MERCARI",
        "itemConditionId": "1",
        "shippingPayerId": "2"
    },
    {
        "id": "m33506011752",
        "sellerId": "465072115",
        "buyerId": "",
        "status": "ITEM_STATUS_ON_SALE",
        "name": "大貫妙子LPレコード/ Aventure",
        "price": "2200",
        "created": "1660658289",
        "updated": "1661032480",
        "thumbnails": [
            "https://static.mercdn.net/c!/w=240,f=webp/thumb/photos/m33506011752_1.jpg?1660658289"
        ],
        "itemType": "ITEM_TYPE_MERCARI",
        "itemConditionId": "4",
        "shippingPayerId": "2"
    },
    {
        "id": "m79887795138",
        "sellerId": "808175157",
        "buyerId": "",
        "status": "ITEM_STATUS_ON_SALE",
        "name": "【大貫妙子】\" GREY SKIES  グレイ・スカイズ\" LP 和モノ",
        "price": "6000",
        "created": "1649721945",
        "updated": "1661275470",
        "thumbnails": [
            "https://static.mercdn.net/c!/w=240,f=webp/thumb/photos/m79887795138_1.jpg?1649721945"
        ],
        "itemType": "ITEM_TYPE_MERCARI",
        "itemConditionId": "1",
        "shippingPayerId": "2"
    },
    {
        "id": "m32149689008",
        "sellerId": "931197331",
        "buyerId": "",
        "status": "ITEM_STATUS_ON_SALE",
        "name": "大貫妙子/愛は幻　レコードストアデイRSD限定7インチ",
        "price": "2333",
        "created": "1651738471",
        "updated": "1660979135",
        "thumbnails": [
            "https://static.mercdn.net/c!/w=240,f=webp/thumb/photos/m32149689008_1.jpg?1651738471"
        ],
        "itemType": "ITEM_TYPE_MERCARI",
        "itemConditionId": "2",
        "shippingPayerId": "2"
    },
    {
        "id": "m23384087428",
        "sellerId": "464090219",
        "buyerId": "",
        "status": "ITEM_STATUS_ON_SALE",
        "name": "大貫妙子　朝のパレット/＜クリア・ピンク(透明ピンク)ヴァイナル＞　レコード",
        "price": "3300",
        "created": "1660728372",
        "updated": "1661218839",
        "thumbnails": [
            "https://static.mercdn.net/c!/w=240,f=webp/thumb/photos/m23384087428_1.jpg?1660728372"
        ],
        "itemType": "ITEM_TYPE_MERCARI",
        "itemConditionId": "1",
        "shippingPayerId": "2"
    },
    {
        "id": "m80678725565",
        "sellerId": "770356068",
        "buyerId": "",
        "status": "ITEM_STATUS_ON_SALE",
        "name": "最終値下げ　大貫妙子  レコード　ARLYTIMES.Cliche 2枚セット",
        "price": "5300",
        "created": "1647140463",
        "updated": "1660913474",
        "thumbnails": [
            "https://static.mercdn.net/c!/w=240,f=webp/thumb/photos/m80678725565_1.jpg?1647140463"
        ],
        "itemType": "ITEM_TYPE_MERCARI",
        "itemConditionId": "4",
        "shippingPayerId": "2"
    }
]